Metadata-Version: 1.2
Name: gsheetvis
Version: 0.0.3
Summary: A Visualizing program which can visualize you data from google sheets 
Home-page: UNKNOWN
Author: Rahul Rathore
Author-email: rathodrahul873@gmail.com
License: NA
Keywords: GSHEET VISUALIZER
Platform: UNKNOWN
Classifier: Development Status :: 5 - Production/Stable
Classifier: Intended Audience :: Education
Classifier: Operating System :: Microsoft :: Windows :: Windows 10
Classifier: Programming Language :: Python :: 3
Requires-Python: >=3.6
